LexaPureToolbox/LexaPureToolbox.py
LexaPureToolbox-1.0.14.dist-info/LICENSE.txt
LexaPureToolbox-1.0.14.dist-info/METADATA
LexaPureToolbox-1.0.14.dist-info/WHEEL
LexaPureToolbox-1.0.14.dist-info/top_level.txt
LexaPureToolbox-1.0.14.dist-info/RECORD
