Metadata-Version: 2.1
Name: LexaPureToolbox
Version: 1.0.14
Summary: Collection of tools developed for LexaPure
Home-page: https://github.com/paulo-lexapure/LexaPuretoolbox
License: MIT
Platform: UNKNOWN
Classifier: License :: OSI Approved :: MIT License
Requires-Dist: requests
Requires-Dist: slacker
Requires-Dist: datetime
Requires-Dist: pymysql
